{
  "teachers": [
    {
      "id": "1",
      "firstname": "Jone ",
      "lastname": "Doe",
      "level": "middle"
    },
    {
      "id": "5",
      "firstname": "Tom  ",
      "lastname": "Smith",
      "level": "senior"
    }
  ],
  "students": [
    {
      "id": "1",
      "firstname": "Shohislom ",
      "lastname": "Ravshanov",
      "level": "intermediate"
    },
    {
      "id": "2",
      "firstname": "Palonchi ",
      "lastname": "Pistonchiev",
      "level": "beginner"
    },
    {
      "id": "4",
      "firstname": "Jane ",
      "lastname": "Doe",
      "level": "intermediate"
    },
    {
      "id": "5",
      "firstname": "Smith ",
      "lastname": "Tomthin",
      "level": "advanced"
    }
  ]
}